[
    {
        "function": "reference",
        "conditions": [
            {
                "condition": "reference",
                "name": "ho9tocraft:item_selector/common_lbset"
            }
        ],
        "name": "ho9tocraft:jobs/common/limit_break"
    },
    {
        "function": "set_lore",
        "conditions": [
            {
                "condition": "reference",
                "name": "ho9tocraft:item_selector/common_lbset"
            }
        ],
        "lore": [
            { "bold": false, "color": "gray", "italic": false, "translate": "skill.exorcist.limit_break.desc", "fallback": "Deals physical damage\n to all nearby enemies that\n can't be taken by the shield.\n(Radius: 6m)" }
        ],
        "mode": "replace_all"
    }
]
